pyblur3/BoxBlur.py
pyblur3/DefocusBlur.py
pyblur3/GaussianBlur.py
pyblur3/LineDictionary.py
pyblur3/LinearMotionBlur.py
pyblur3/PsfBlur.py
pyblur3/RandomizedBlur.py
pyblur3/__init__.py
pyblur3/psf.pkl
pyblur3-0.1.2.dist-info/LICENSE
pyblur3-0.1.2.dist-info/METADATA
pyblur3-0.1.2.dist-info/WHEEL
pyblur3-0.1.2.dist-info/top_level.txt
pyblur3-0.1.2.dist-info/RECORD
