Metadata-Version: 2.1
Name: pyblur3
Version: 0.1.2
Summary: Image blurring routines
Home-page: http://github.com/desmoteo/pyblur3
Author: Matteo Ferrabone
Author-email: matteo.ferrabone@gmail.com
License: MIT
Keywords: blur
Platform: UNKNOWN
Classifier: Development Status :: 3 - Alpha
Classifier: License :: OSI Approved :: MIT License
Classifier: Intended Audience :: Developers
Classifier: Intended Audience :: Science/Research
Classifier: Programming Language :: Python :: 3.6
Classifier: Topic :: Multimedia :: Graphics
Requires-Dist: numpy
Requires-Dist: pillow
Requires-Dist: scikit-image
Requires-Dist: scipy
